{"id":"word","name":"Word","iconName":"work","color":"0078D4","buttons":[{"id":"wd_1","label":"Kalın","iconName":"format_bold","color":"3B82F6","actionType":"hotkey","actionData":"ctrl+b"},{"id":"wd_2","label":"İtalik","iconName":"format_italic","color":"3B82F6","actionType":"hotkey","actionData":"ctrl+i"},{"id":"wd_3","label":"Altı Çizili","iconName":"format_underlined","color":"3B82F6","actionType":"hotkey","actionData":"ctrl+u"},{"id":"wd_4","label":"Ortala","iconName":"format_align_center","color":"8B5CF6","actionType":"hotkey","actionData":"ctrl+e"},{"id":"wd_5","label":"Kaydet","iconName":"save","color":"22C55E","actionType":"hotkey","actionData":"ctrl+s"},{"id":"wd_6","label":"Yazdır","iconName":"print","color":"64748B","actionType":"hotkey","actionData":"ctrl+p"}]}